{
  "main": {
    "name": "Raul Sanz",
    "description": "Full-Stack Developer / Designer",
    "bio": [
      {
        "text": "Front end web developer with a background in digital design ready to provide my experience in UX, marketing and advertising."
      },
      {
        "text": "After completing the accredited University of Manchester Coding Boot Camp, I am looking for a challenging position where I can focus and improve upon my passion for coding."
      },
      {
        "text": "My strengths are creativity, teamwork, and building projects from ideation to execution."
      }
    ],

    "contactmessage": "Feel free to contact me via email, the form, or LinkedIn",
    "email": "sanzdiaz.raul@gmail.com",
    "phone": "+44 (0)7731592441",
    "github": "https://github.com/itsraulsanz",
    "linkedin": "https://linkedin.com/in/raulsd",
    "address": {
      "city": "Manchester",
      "country": "UK"
    },
    "website": "https://github.com/itsraulsanz",
    "resumedownload": "pdf/RaulSanz_CV.pdf",
    "social": [
      {
        "name": "github",
        "url": "https://github.com/itsraulsanz",
        "className": "fa fa-github"
      },
      {
        "name": "linkedin",
        "url": "https://www.linkedin.com/in/raulsd/",
        "className": "fa fa-linkedin"
      }
    ]
  },
  "resume": {
    "education": [
      {
        "school": "University of Manchester",
        "grade": "A+ Academic Average",
        "degree": "Coding Bootcamp Certificate",
        "graduated": "August 2021",
        "description": "An intensive 6-month boot camp dedicated to building web applications. Skills learned consisted of HTML5, CSS3, Javascript, JQuery, Bootstrap, Node Js, MySQL, MongoDB, Express, Handelbars.js and ReactJS."
      },
      {
        "school": "ESDi - Ramon Llull University of Sabadell",
        "grade": "2.1 Equivalent",
        "degree": "Bachelor's of Electronic Art and Digital Design",
        "graduated": "August 2009",
        "description": "The degree developed skills in design, programming and animation including modules on: HTML, CSS, Javascript, PHP, XML, Databases and Flash ActionScript."
      }
    ],
    "work": [
      {
        "company": "JD Sports",
        "location": "Manchester",
        "title": "Graphic Designer",
        "years": "2018 - Present",
        "description": "Managed and developed international campaigns for brands such as Nike and Adidas across: email, on-site banners, apps and social media. Created layouts and templates to optimise designs and work flow."
      },
      {
        "company": "LOLA Mullen LOWE",
        "location": "Barcelona",
        "title": "Visual Designer",
        "years": "2014 - 2017",
        "description": "Developed original solutions for clients such as Seat, while maintaining creative, technical and brand standards. Designed campaigns for online and print across websites, landing pages, banners, mailers, prints and billboards."
      },
      {
        "company": "Emailing Network",
        "location": "Barcelona",
        "title": "Web Designer & Front-End",
        "years": "2011 - 2014",
        "description": "Designed and programmed emails, using A/B testing to enhance click-through conversion and optimise outcomes. Rebranded clicplan.com and oferting.es which drove international sales growth."
      },
      {
        "company": "Ogilvy & Mather",
        "location": "Barcelona",
        "title": "Web Designer & Front-End",
        "years": "2009 - 2011",
        "description": "Designed and programmed segmented email campaigns, landing pages, animated banners, and website updates for clients such as Nestle, Amstel and CaixaBank."
      }
    ],
    "skills": [
      {
        "name": "HTML / CSS / Bootstrap",
        "level": "90%"
      },
      {
        "name": "SQL, NoSQL",
        "level": "50%"
      },
      {
        "name": "Github, Heroku",
        "level": "80%"
      },
      {
        "name": "NodeJS / ExpressJS",
        "level": "80%"
      },
      {
        "name": "JavaScript",
        "level": "90%"
      },
      {
        "name": "React",
        "level": "90%"
      },
      {
        "name": "GraphQL",
        "level": "70%"
      },
      {
        "name": "APIs",
        "level": "90%"
      },
      {
        "name": "Photoshop",
        "level": "90%"
      },
      {
        "name": "Illustrator / Indesign",
        "level": "90%"
      },
      {
        "name": "Adobe XD / Sketch",
        "level": "90%"
      }
    ],
    "personalSkills": [
      "Creativity",
      "Problem-Solving",
      "Self-upskilling",
      "Innovative"
    ],
    "languages": ["English", "Spanish", "Catalan"],
    "hobbies": [
      "Traveling",
      "Music, gigs, festivals",
      "Art, photography",
      "Cinema, TV Shows"
    ]
  },
  "portfolio": {
    "projects": [
      {
        "title": "Castaway",
        "description": "Podcasting app designed to make the search and navigation easier.",
        "image": "project_9.png",
        "technology": "MERN stack set up, with Apollo Server and graphQL.",
        "url": "https://podcastaway-app.herokuapp.com",
        "repo": "https://github.com/itsraulsanz/castaway-app"
      },
      {
        "title": "Pose-It",
        "description": "Fashion App designed to let users build up a wardrobe of inspiration on their digital device. A full stack web development application, it allows users to record outfits, uploads photos and details, filter all user posts to find outfits to match their specific criteria, save them to their personal dashboard and delete any items that they are no longer interested in.",
        "image": "project_8.jpg",
        "technology": "Node.js, Express.js, Handlebars.js, MySQL, Sequelize ORM, CSS, Git Hub.",
        "url": "https://pose-it-app.herokuapp.com/",
        "repo": "https://github.com/itsraulsanz/pose-it-app"
      },
      {
        "title": "Blog",
        "description": "A CMS-style blog site where users can publish their blog posts and comment on other developers’ posts as well. The app follows the MVC paradigm in its architectural structure, using Handlebars.js as the templating language, Sequelize as the ORM, and the express-session npm package for authentication.",
        "image": "project_7.jpg",
        "technology": "Node.js, Express.js, Handlebars.js, MySQL, Sequelize ORM, CSS, Git Hub.",
        "url": "https://raul-tech-blog.herokuapp.com/",
        "repo": "https://github.com/itsraulsanz/Raul-Blog"
      },
      {
        "title": "Note-Taker",
        "description": "Application to write and save notes. This application uses an Express.js back end and saves and retrieves note data from a JSON file.",
        "image": "project_6.jpg",
        "technology": "Express.js, HTML, CSS, Git Hub.",
        "url": "https://murmuring-island-71920.herokuapp.com/",
        "repo": "https://github.com/itsraulsanz/Note-Taker"
      },
      {
        "title": "Hammered Horror",
        "description": "The Hammered Horror application is a web-based film generator application. During the pandemic people are watching a lot more films. As a team we decided to develop an application based on the Horror genre",
        "image": "project_5.jpg",
        "technology": "HTML, CSS, Frameworks, JavaScript, API’s, Git Hub.",
        "url": "https://itsraulsanz.github.io/trilogy-film-project/index.html",
        "repo": "https://github.com/itsraulsanz/trilogy-film-project"
      },
      {
        "title": "Weather Dashboard",
        "description": "Weather outlook for multiple cities that shows the current and the weather for the next 5 days. It's built using [OpenWeather API] to retrieve weather data for cities.",
        "image": "project_4.jpg",
        "technology": "HTML, CSS, Frameworks, JavaScript, API’s, Git Hub.",
        "url": "https://itsraulsanz.github.io/weather-forecast/",
        "repo": "https://github.com/itsraulsanz/weather-forecast"
      },
      {
        "title": "Work Day Scheduler",
        "description": "Calendar application that allows a user to save events for each business hour of the day. The current day and hour is displayed in the header. Each timeblock is colored indicating whether it is in the past, present, or future.",
        "image": "project_3.jpg",
        "technology": "HTML, CSS, Frameworks, JavaScript, Git Hub.",
        "url": "https://itsraulsanz.github.io/plan-your-day/",
        "repo": "https://github.com/itsraulsanz/plan-your-day"
      }
    ]
  }
}
